kontext_copilot/__init__.py
kontext_copilot/api/README.md
kontext_copilot/api/copilot/__init__.py
kontext_copilot/api/copilot/_requests_handler.py
kontext_copilot/api/data_providers/__init__.py
kontext_copilot/api/data_providers/_requests_handler.py
kontext_copilot/api/data_sources/__init__.py
kontext_copilot/api/data_sources/_requests_handler.py
kontext_copilot/api/prompts/__init__.py
kontext_copilot/api/prompts/_requests_handler.py
kontext_copilot/api/settings/__init__.py
kontext_copilot/api/settings/_requests_handler.py
kontext_copilot/copilot/__init__.py
kontext_copilot/copilot/_copilot_orchestrator.py
kontext_copilot/copilot/_copilot_session.py
kontext_copilot/copilot/_prompt_factory.py
kontext_copilot/copilot/prompts/sentiment-analysis.md
kontext_copilot/copilot/prompts/system-prompt-da-metadata-file-source.md
kontext_copilot/copilot/prompts/system-prompt-da-metadata-refined.md
kontext_copilot/copilot/prompts/system-prompt-da-metadata.md
kontext_copilot/copilot/prompts/system-prompt-default.md
kontext_copilot/copilot/prompts/text-to-sql-static.md
kontext_copilot/copilot/prompts.json
kontext_copilot/copilot/tools/_base_tool.py
kontext_copilot/copilot/tools/_chart_renderer.py
kontext_copilot/copilot/tools/_charts_recommend_tool.py
kontext_copilot/copilot/tools/_data_analyser.py
kontext_copilot/copilot/tools/_extract_sql_tool.py
kontext_copilot/copilot/tools/_llm_chat_tool.py
kontext_copilot/copilot/tools/_questions_recommend_tool.py
kontext_copilot/copilot/tools/_run_sql_tool.py
kontext_copilot/data/Chinook-LICENSE.md
kontext_copilot/data/Chinook_Sqlite.db
kontext_copilot/data/__init__.py
kontext_copilot/data/alembic/README
kontext_copilot/data/alembic/alembic.ini
kontext_copilot/data/alembic/env.py
kontext_copilot/data/alembic/script.py.mako
kontext_copilot/data/alembic/versions/a60eafe5e3f9_init.py
kontext_copilot/data/models/__init__.py
kontext_copilot/data/models/_db_models.py
kontext_copilot/data/schemas/__init__.py
kontext_copilot/data/schemas/_common.py
kontext_copilot-0.7.3.dist-info/LICENSE
kontext_copilot-0.7.3.dist-info/METADATA
kontext_copilot-0.7.3.dist-info/WHEEL
kontext_copilot-0.7.3.dist-info/entry_points.txt
kontext_copilot-0.7.3.dist-info/RECORD
