Metadata-Version: 2.1
Name: kontext-copilot
Version: 0.7.3
Summary: Kontext Copilot is an AI empowered assistant for data analytics that can run on your local computer.
Home-page: https://kontext.tech/copilot
License: MIT
Author: Kontext
Author-email: enquiry@kontext.tech
Requires-Python: >=3.9,<4.0
Classifier: License :: OSI Approved :: MIT License
Classifier: Programming Language :: Python :: 3
Classifier: Programming Language :: Python :: 3.9
Classifier: Programming Language :: Python :: 3.10
Classifier: Programming Language :: Python :: 3.11
Classifier: Programming Language :: Python :: 3.12
Requires-Dist: alembic (>=1.13.2,<2.0.0)
Requires-Dist: colorlog (>=6.8.2,<7.0.0)
Requires-Dist: duckdb (>=1.0.0,<2.0.0)
Requires-Dist: duckdb-engine (>=0.13.1,<0.14.0)
Requires-Dist: fastapi (>=0.111.0,<0.112.0)
Requires-Dist: oracledb (>=2.4.1,<3.0.0)
Requires-Dist: pre-commit (>=3.7.1,<4.0.0)
Requires-Dist: psycopg[binary] (>=3.2.1,<4.0.0)
Requires-Dist: pyarrow (>=17.0.0,<18.0.0)
Requires-Dist: pydantic (>=2.8.2,<3.0.0)
Requires-Dist: pyodbc (>=5.1.0,<6.0.0)
Requires-Dist: python-dotenv (>=1.0.1,<2.0.0)
Requires-Dist: sqlalchemy (>=2.0.31,<3.0.0)
Requires-Dist: typing-extensions (>=4.10.0,<5.0.0)
Project-URL: Repository, https://github.com/kontext-tech/kontext-copilot
